[
    {
        "key": "datr",
        "value": "_xgtagr-kDDC4luFpAbfuQgZ",
        "domain": "facebook.com",
        "path": "/",
        "hostOnly": false,
        "creation": "2026-07-09T07:11:27.180Z",
        "lastAccessed": "2026-07-09T07:11:27.182Z"
    },
    {
        "key": "sb",
        "value": "_xgtaoXwM8-5Zox-4V_3dCGF",
        "domain": "facebook.com",
        "path": "/",
        "hostOnly": false,
        "creation": "2026-07-09T07:11:27.182Z",
        "lastAccessed": "2026-07-09T07:11:27.182Z"
    },
    {
        "key": "ps_l",
        "value": "1",
        "domain": "facebook.com",
        "path": "/",
        "hostOnly": false,
        "creation": "2026-07-09T07:11:27.182Z",
        "lastAccessed": "2026-07-09T07:11:27.182Z"
    },
    {
        "key": "ps_n",
        "value": "1",
        "domain": "facebook.com",
        "path": "/",
        "hostOnly": false,
        "creation": "2026-07-09T07:11:27.182Z",
        "lastAccessed": "2026-07-09T07:11:27.182Z"
    },
    {
        "key": "pas",
        "value": "61568216267383%3AgtiZQTyXL1%2C61590734487076%3A747rFCJRUp",
        "domain": "facebook.com",
        "path": "/",
        "hostOnly": false,
        "creation": "2026-07-09T07:11:27.182Z",
        "lastAccessed": "2026-07-09T07:11:27.182Z"
    },
    {
        "key": "c_user",
        "value": "61590734487076",
        "domain": "facebook.com",
        "path": "/",
        "hostOnly": false,
        "creation": "2026-07-09T07:11:27.182Z",
        "lastAccessed": "2026-07-09T07:11:27.182Z"
    },
    {
        "key": "xs",
        "value": "24%3Azl8oYxDtrhLoGw%3A2%3A1782828299%3A-1%3A-1",
        "domain": "facebook.com",
        "path": "/",
        "hostOnly": false,
        "creation": "2026-07-09T07:11:27.182Z",
        "lastAccessed": "2026-07-09T07:11:27.182Z"
    },
    {
        "key": "vpd",
        "value": "v1%3B688x360x1.7004296779632568",
        "domain": "facebook.com",
        "path": "/",
        "hostOnly": false,
        "creation": "2026-07-09T07:11:27.182Z",
        "lastAccessed": "2026-07-09T07:11:27.182Z"
    },
    {
        "key": "locale",
        "value": "en_GB",
        "domain": "facebook.com",
        "path": "/",
        "hostOnly": false,
        "creation": "2026-07-09T07:11:27.182Z",
        "lastAccessed": "2026-07-09T07:11:27.182Z"
    },
    {
        "key": "fr",
        "value": "0XPHy2s0bK67SIRxa.AWdCJjgyTX6z9DdB1aJu9IXicqsNv7fD94cc0K67397aUiOT4FM.BqLRj_..AAA.0.0.BqT0mV.AWeu2HcD-wReirLJ1MxF1AEoQKk",
        "domain": "facebook.com",
        "path": "/",
        "hostOnly": false,
        "creation": "2026-07-09T07:11:27.182Z",
        "lastAccessed": "2026-07-09T07:11:27.182Z"
    },
    {
        "key": "fbl_st",
        "value": "100638405%3BT%3A29726351",
        "domain": "facebook.com",
        "path": "/",
        "hostOnly": false,
        "creation": "2026-07-09T07:11:27.182Z",
        "lastAccessed": "2026-07-09T07:11:27.182Z"
    },
    {
        "key": "wl_cbv",
        "value": "v2%3Bclient_version%3A3209%3Btimestamp%3A1783581078",
        "domain": "facebook.com",
        "path": "/",
        "hostOnly": false,
        "creation": "2026-07-09T07:11:27.182Z",
        "lastAccessed": "2026-07-09T07:11:27.182Z"
    }
]
